LICENSE.txt
setup.cfg
setup.py
telecore/telecore.py
telecore.egg-info/PKG-INFO
telecore.egg-info/SOURCES.txt
telecore.egg-info/dependency_links.txt
telecore.egg-info/requires.txt
telecore.egg-info/top_level.txt