Metadata-Version: 2.1
Name: telecore
Version: 0.0.4
Summary: a library for telegram bot messenger
Home-page: 
Download-URL: https://github.com/user/reponame/archive/v_01.tar.gz
Author: Host1let
Author-email: hslhostlet@gmail.com
License: MIT
Keywords: SOME,MEANINGFULL,KEYWORDS
Classifier: Development Status :: 3 - Alpha
Classifier: Intended Audience :: Developers
Classifier: Topic :: Software Development :: Build Tools
Classifier: License :: OSI Approved :: MIT License
Classifier: Programming Language :: Python :: 3
Classifier: Programming Language :: Python :: 3.4
Classifier: Programming Language :: Python :: 3.5
Classifier: Programming Language :: Python :: 3.6
License-File: LICENSE.txt
